pyfgtconflib/__init__.py
pyfgtconflib/pyfgtconflib.py
pyfgtconflib-0.0.2.dist-info/LICENSE
pyfgtconflib-0.0.2.dist-info/METADATA
pyfgtconflib-0.0.2.dist-info/WHEEL
pyfgtconflib-0.0.2.dist-info/top_level.txt
pyfgtconflib-0.0.2.dist-info/RECORD
