Metadata-Version: 2.1
Name: pyfgtconflib
Version: 0.0.2
Summary: Python FortiGate Config Library
Home-page: https://github.com/fortinetps/pyfgtconflib
Author: Don Yao
Author-email: dyao@fortinet.com
Project-URL: Bug Tracker, https://github.com/fortinetps/pyfgtconflib/issues
Classifier: Programming Language :: Python :: 3
Classifier: License :: OSI Approved :: GNU General Public License v3 (GPLv3)
Classifier: Operating System :: OS Independent
Requires-Python: >=3.6
License-File: LICENSE
